tsp_optimisation/__init__.py
tsp_optimisation/data_loader.py
tsp_optimisation/resolution.py
tsp_optimisation/ville.py
tsp_optimisation/voyageur.py
tsp_optimisation-0.1.0.dist-info/entry_points.txt
tsp_optimisation-0.1.0.dist-info/METADATA
tsp_optimisation-0.1.0.dist-info/WHEEL
tsp_optimisation-0.1.0.dist-info/RECORD
