Metadata-Version: 2.4
Name: tsp-optimisation
Version: 0.1.0
Summary: Résolution du problème du voyageur de commerce (TSP) avec contraintes et affichage du parcours optimal.
License: MIT
Author: Amaidi Chaima
Author-email: amaidiamaidi13@gmail.com
Requires-Python: >=3.10,<4.0
Classifier: License :: OSI Approved :: MIT License
Classifier: Programming Language :: Python :: 3
Classifier: Programming Language :: Python :: 3.10
Classifier: Programming Language :: Python :: 3.11
Classifier: Programming Language :: Python :: 3.12
Classifier: Programming Language :: Python :: 3.13
Classifier: Programming Language :: Python :: 3.14
